pysimular/__init__.py
pysimular/browser.py
pysimular/exceptions.py
pysimular/tab.py
pysimular-0.1.2.dist-info/LICENSE
pysimular-0.1.2.dist-info/METADATA
pysimular-0.1.2.dist-info/WHEEL
pysimular-0.1.2.dist-info/top_level.txt
pysimular-0.1.2.dist-info/RECORD
