Metadata-Version: 2.1
Name: pysimular
Version: 0.1.2
Summary: Python API for Simular agents
Home-page: https://github.com/simular-ai/pysimular
Author: Simular
Author-email: support@simular.ai
Classifier: Programming Language :: Python :: 3
Classifier: License :: OSI Approved :: Apache Software License
Classifier: Operating System :: OS Independent
Requires-Python: >=3.6
License-File: LICENSE
Requires-Dist: requests>=2.25.1
Requires-Dist: aiohttp>=3.8.0
Requires-Dist: pyobjc
